{
  "version": "5",
  "dialect": "mysql",
  "id": "1b15400b-a3ab-4e9a-8d37-02f1f49de066",
  "prevId": "081249e4-2025-4d98-8755-0aa75e2f575a",
  "tables": {
    "certificates": {
      "name": "certificates",
      "columns": {
        "id": {
          "name": "id",
          "type": "int",
          "primaryKey": false,
          "notNull": true,
          "autoincrement": true
        },
        "enrollmentId": {
          "name": "enrollmentId",
          "type": "int",
          "primaryKey": false,
          "notNull": true,
          "autoincrement": false
        },
        "userId": {
          "name": "userId",
          "type": "int",
          "primaryKey": false,
          "notNull": true,
          "autoincrement": false
        },
        "certificateNumber": {
          "name": "certificateNumber",
          "type": "varchar(255)",
          "primaryKey": false,
          "notNull": false,
          "autoincrement": false
        },
        "programType": {
          "name": "programType",
          "type": "enum('bls','acls','pals','fellowship')",
          "primaryKey": false,
          "notNull": true,
          "autoincrement": false
        },
        "issueDate": {
          "name": "issueDate",
          "type": "timestamp",
          "primaryKey": false,
          "notNull": true,
          "autoincrement": false
        },
        "expiryDate": {
          "name": "expiryDate",
          "type": "timestamp",
          "primaryKey": false,
          "notNull": false,
          "autoincrement": false
        },
        "certificateUrl": {
          "name": "certificateUrl",
          "type": "text",
          "primaryKey": false,
          "notNull": false,
          "autoincrement": false
        },
        "verificationCode": {
          "name": "verificationCode",
          "type": "varchar(255)",
          "primaryKey": false,
          "notNull": false,
          "autoincrement": false
        },
        "createdAt": {
          "name": "createdAt",
          "type": "timestamp",
          "primaryKey": false,
          "notNull": true,
          "autoincrement": false,
          "default": "(now())"
        }
      },
      "indexes": {},
      "foreignKeys": {},
      "compositePrimaryKeys": {
        "certificates_id": {
          "name": "certificates_id",
          "columns": [
            "id"
          ]
        }
      },
      "uniqueConstraints": {
        "certificates_certificateNumber_unique": {
          "name": "certificates_certificateNumber_unique",
          "columns": [
            "certificateNumber"
          ]
        },
        "certificates_verificationCode_unique": {
          "name": "certificates_verificationCode_unique",
          "columns": [
            "verificationCode"
          ]
        }
      },
      "checkConstraint": {}
    },
    "enrollments": {
      "name": "enrollments",
      "columns": {
        "id": {
          "name": "id",
          "type": "int",
          "primaryKey": false,
          "notNull": true,
          "autoincrement": true
        },
        "userId": {
          "name": "userId",
          "type": "int",
          "primaryKey": false,
          "notNull": true,
          "autoincrement": false
        },
        "programType": {
          "name": "programType",
          "type": "enum('bls','acls','pals','fellowship')",
          "primaryKey": false,
          "notNull": true,
          "autoincrement": false
        },
        "trainingDate": {
          "name": "trainingDate",
          "type": "timestamp",
          "primaryKey": false,
          "notNull": true,
          "autoincrement": false
        },
        "paymentStatus": {
          "name": "paymentStatus",
          "type": "enum('pending','partial','completed')",
          "primaryKey": false,
          "notNull": false,
          "autoincrement": false,
          "default": "'pending'"
        },
        "amountPaid": {
          "name": "amountPaid",
          "type": "int",
          "primaryKey": false,
          "notNull": false,
          "autoincrement": false,
          "default": 0
        },
        "ahaPrecourseCompleted": {
          "name": "ahaPrecourseCompleted",
          "type": "boolean",
          "primaryKey": false,
          "notNull": false,
          "autoincrement": false,
          "default": false
        },
        "ahaCertificateUrl": {
          "name": "ahaCertificateUrl",
          "type": "text",
          "primaryKey": false,
          "notNull": false,
          "autoincrement": false
        },
        "certificateVerified": {
          "name": "certificateVerified",
          "type": "boolean",
          "primaryKey": false,
          "notNull": false,
          "autoincrement": false,
          "default": false
        },
        "reminderSent": {
          "name": "reminderSent",
          "type": "boolean",
          "primaryKey": false,
          "notNull": false,
          "autoincrement": false,
          "default": false
        },
        "reminderSentAt": {
          "name": "reminderSentAt",
          "type": "timestamp",
          "primaryKey": false,
          "notNull": false,
          "autoincrement": false
        },
        "createdAt": {
          "name": "createdAt",
          "type": "timestamp",
          "primaryKey": false,
          "notNull": true,
          "autoincrement": false,
          "default": "(now())"
        },
        "updatedAt": {
          "name": "updatedAt",
          "type": "timestamp",
          "primaryKey": false,
          "notNull": true,
          "autoincrement": false,
          "onUpdate": true,
          "default": "(now())"
        }
      },
      "indexes": {},
      "foreignKeys": {},
      "compositePrimaryKeys": {
        "enrollments_id": {
          "name": "enrollments_id",
          "columns": [
            "id"
          ]
        }
      },
      "uniqueConstraints": {},
      "checkConstraint": {}
    },
    "institutionalAccounts": {
      "name": "institutionalAccounts",
      "columns": {
        "id": {
          "name": "id",
          "type": "int",
          "primaryKey": false,
          "notNull": true,
          "autoincrement": true
        },
        "userId": {
          "name": "userId",
          "type": "int",
          "primaryKey": false,
          "notNull": true,
          "autoincrement": false
        },
        "companyName": {
          "name": "companyName",
          "type": "varchar(255)",
          "primaryKey": false,
          "notNull": true,
          "autoincrement": false
        },
        "industry": {
          "name": "industry",
          "type": "varchar(255)",
          "primaryKey": false,
          "notNull": false,
          "autoincrement": false
        },
        "staffCount": {
          "name": "staffCount",
          "type": "int",
          "primaryKey": false,
          "notNull": false,
          "autoincrement": false
        },
        "contactName": {
          "name": "contactName",
          "type": "varchar(255)",
          "primaryKey": false,
          "notNull": true,
          "autoincrement": false
        },
        "contactEmail": {
          "name": "contactEmail",
          "type": "varchar(320)",
          "primaryKey": false,
          "notNull": true,
          "autoincrement": false
        },
        "contactPhone": {
          "name": "contactPhone",
          "type": "varchar(20)",
          "primaryKey": false,
          "notNull": false,
          "autoincrement": false
        },
        "status": {
          "name": "status",
          "type": "enum('prospect','active','inactive')",
          "primaryKey": false,
          "notNull": false,
          "autoincrement": false,
          "default": "'prospect'"
        },
        "createdAt": {
          "name": "createdAt",
          "type": "timestamp",
          "primaryKey": false,
          "notNull": true,
          "autoincrement": false,
          "default": "(now())"
        },
        "updatedAt": {
          "name": "updatedAt",
          "type": "timestamp",
          "primaryKey": false,
          "notNull": true,
          "autoincrement": false,
          "onUpdate": true,
          "default": "(now())"
        }
      },
      "indexes": {},
      "foreignKeys": {},
      "compositePrimaryKeys": {
        "institutionalAccounts_id": {
          "name": "institutionalAccounts_id",
          "columns": [
            "id"
          ]
        }
      },
      "uniqueConstraints": {},
      "checkConstraint": {}
    },
    "institutionalInquiries": {
      "name": "institutionalInquiries",
      "columns": {
        "id": {
          "name": "id",
          "type": "int",
          "primaryKey": false,
          "notNull": true,
          "autoincrement": true
        },
        "companyName": {
          "name": "companyName",
          "type": "varchar(255)",
          "primaryKey": false,
          "notNull": true,
          "autoincrement": false
        },
        "staffCount": {
          "name": "staffCount",
          "type": "int",
          "primaryKey": false,
          "notNull": true,
          "autoincrement": false
        },
        "specificNeeds": {
          "name": "specificNeeds",
          "type": "text",
          "primaryKey": false,
          "notNull": false,
          "autoincrement": false
        },
        "contactName": {
          "name": "contactName",
          "type": "varchar(255)",
          "primaryKey": false,
          "notNull": true,
          "autoincrement": false
        },
        "contactEmail": {
          "name": "contactEmail",
          "type": "varchar(320)",
          "primaryKey": false,
          "notNull": true,
          "autoincrement": false
        },
        "contactPhone": {
          "name": "contactPhone",
          "type": "varchar(20)",
          "primaryKey": false,
          "notNull": false,
          "autoincrement": false
        },
        "status": {
          "name": "status",
          "type": "enum('new','contacted','qualified','converted','rejected')",
          "primaryKey": false,
          "notNull": false,
          "autoincrement": false,
          "default": "'new'"
        },
        "createdAt": {
          "name": "createdAt",
          "type": "timestamp",
          "primaryKey": false,
          "notNull": true,
          "autoincrement": false,
          "default": "(now())"
        },
        "updatedAt": {
          "name": "updatedAt",
          "type": "timestamp",
          "primaryKey": false,
          "notNull": true,
          "autoincrement": false,
          "onUpdate": true,
          "default": "(now())"
        }
      },
      "indexes": {},
      "foreignKeys": {},
      "compositePrimaryKeys": {
        "institutionalInquiries_id": {
          "name": "institutionalInquiries_id",
          "columns": [
            "id"
          ]
        }
      },
      "uniqueConstraints": {},
      "checkConstraint": {}
    },
    "learnerProgress": {
      "name": "learnerProgress",
      "columns": {
        "id": {
          "name": "id",
          "type": "int",
          "primaryKey": false,
          "notNull": true,
          "autoincrement": true
        },
        "userId": {
          "name": "userId",
          "type": "int",
          "primaryKey": false,
          "notNull": true,
          "autoincrement": false
        },
        "enrollmentId": {
          "name": "enrollmentId",
          "type": "int",
          "primaryKey": false,
          "notNull": true,
          "autoincrement": false
        },
        "progressPercentage": {
          "name": "progressPercentage",
          "type": "int",
          "primaryKey": false,
          "notNull": false,
          "autoincrement": false,
          "default": 0
        },
        "modulesCompleted": {
          "name": "modulesCompleted",
          "type": "int",
          "primaryKey": false,
          "notNull": false,
          "autoincrement": false,
          "default": 0
        },
        "totalModules": {
          "name": "totalModules",
          "type": "int",
          "primaryKey": false,
          "notNull": false,
          "autoincrement": false,
          "default": 0
        },
        "badges": {
          "name": "badges",
          "type": "text",
          "primaryKey": false,
          "notNull": false,
          "autoincrement": false
        },
        "leaderboardRank": {
          "name": "leaderboardRank",
          "type": "int",
          "primaryKey": false,
          "notNull": false,
          "autoincrement": false
        },
        "lastActivityAt": {
          "name": "lastActivityAt",
          "type": "timestamp",
          "primaryKey": false,
          "notNull": false,
          "autoincrement": false
        },
        "createdAt": {
          "name": "createdAt",
          "type": "timestamp",
          "primaryKey": false,
          "notNull": true,
          "autoincrement": false,
          "default": "(now())"
        },
        "updatedAt": {
          "name": "updatedAt",
          "type": "timestamp",
          "primaryKey": false,
          "notNull": true,
          "autoincrement": false,
          "onUpdate": true,
          "default": "(now())"
        }
      },
      "indexes": {},
      "foreignKeys": {},
      "compositePrimaryKeys": {
        "learnerProgress_id": {
          "name": "learnerProgress_id",
          "columns": [
            "id"
          ]
        }
      },
      "uniqueConstraints": {},
      "checkConstraint": {}
    },
    "payments": {
      "name": "payments",
      "columns": {
        "id": {
          "name": "id",
          "type": "int",
          "primaryKey": false,
          "notNull": true,
          "autoincrement": true
        },
        "enrollmentId": {
          "name": "enrollmentId",
          "type": "int",
          "primaryKey": false,
          "notNull": true,
          "autoincrement": false
        },
        "userId": {
          "name": "userId",
          "type": "int",
          "primaryKey": false,
          "notNull": true,
          "autoincrement": false
        },
        "amount": {
          "name": "amount",
          "type": "int",
          "primaryKey": false,
          "notNull": true,
          "autoincrement": false
        },
        "paymentMethod": {
          "name": "paymentMethod",
          "type": "enum('mpesa','bank_transfer','card')",
          "primaryKey": false,
          "notNull": true,
          "autoincrement": false
        },
        "transactionId": {
          "name": "transactionId",
          "type": "varchar(255)",
          "primaryKey": false,
          "notNull": false,
          "autoincrement": false
        },
        "status": {
          "name": "status",
          "type": "enum('pending','completed','failed')",
          "primaryKey": false,
          "notNull": false,
          "autoincrement": false,
          "default": "'pending'"
        },
        "smsConfirmationSent": {
          "name": "smsConfirmationSent",
          "type": "boolean",
          "primaryKey": false,
          "notNull": false,
          "autoincrement": false,
          "default": false
        },
        "createdAt": {
          "name": "createdAt",
          "type": "timestamp",
          "primaryKey": false,
          "notNull": true,
          "autoincrement": false,
          "default": "(now())"
        },
        "updatedAt": {
          "name": "updatedAt",
          "type": "timestamp",
          "primaryKey": false,
          "notNull": true,
          "autoincrement": false,
          "onUpdate": true,
          "default": "(now())"
        }
      },
      "indexes": {},
      "foreignKeys": {},
      "compositePrimaryKeys": {
        "payments_id": {
          "name": "payments_id",
          "columns": [
            "id"
          ]
        }
      },
      "uniqueConstraints": {},
      "checkConstraint": {}
    },
    "platformSettings": {
      "name": "platformSettings",
      "columns": {
        "id": {
          "name": "id",
          "type": "int",
          "primaryKey": false,
          "notNull": true,
          "autoincrement": true
        },
        "settingKey": {
          "name": "settingKey",
          "type": "varchar(255)",
          "primaryKey": false,
          "notNull": true,
          "autoincrement": false
        },
        "settingValue": {
          "name": "settingValue",
          "type": "text",
          "primaryKey": false,
          "notNull": false,
          "autoincrement": false
        },
        "createdAt": {
          "name": "createdAt",
          "type": "timestamp",
          "primaryKey": false,
          "notNull": true,
          "autoincrement": false,
          "default": "(now())"
        },
        "updatedAt": {
          "name": "updatedAt",
          "type": "timestamp",
          "primaryKey": false,
          "notNull": true,
          "autoincrement": false,
          "onUpdate": true,
          "default": "(now())"
        }
      },
      "indexes": {},
      "foreignKeys": {},
      "compositePrimaryKeys": {
        "platformSettings_id": {
          "name": "platformSettings_id",
          "columns": [
            "id"
          ]
        }
      },
      "uniqueConstraints": {
        "platformSettings_settingKey_unique": {
          "name": "platformSettings_settingKey_unique",
          "columns": [
            "settingKey"
          ]
        }
      },
      "checkConstraint": {}
    },
    "referrals": {
      "name": "referrals",
      "columns": {
        "id": {
          "name": "id",
          "type": "int",
          "primaryKey": false,
          "notNull": true,
          "autoincrement": true
        },
        "referrerId": {
          "name": "referrerId",
          "type": "int",
          "primaryKey": false,
          "notNull": true,
          "autoincrement": false
        },
        "referredUserId": {
          "name": "referredUserId",
          "type": "int",
          "primaryKey": false,
          "notNull": true,
          "autoincrement": false
        },
        "status": {
          "name": "status",
          "type": "enum('pending','completed','failed')",
          "primaryKey": false,
          "notNull": false,
          "autoincrement": false,
          "default": "'pending'"
        },
        "rewardAmount": {
          "name": "rewardAmount",
          "type": "int",
          "primaryKey": false,
          "notNull": false,
          "autoincrement": false
        },
        "rewardProcessedAt": {
          "name": "rewardProcessedAt",
          "type": "timestamp",
          "primaryKey": false,
          "notNull": false,
          "autoincrement": false
        },
        "createdAt": {
          "name": "createdAt",
          "type": "timestamp",
          "primaryKey": false,
          "notNull": true,
          "autoincrement": false,
          "default": "(now())"
        },
        "updatedAt": {
          "name": "updatedAt",
          "type": "timestamp",
          "primaryKey": false,
          "notNull": true,
          "autoincrement": false,
          "onUpdate": true,
          "default": "(now())"
        }
      },
      "indexes": {},
      "foreignKeys": {},
      "compositePrimaryKeys": {
        "referrals_id": {
          "name": "referrals_id",
          "columns": [
            "id"
          ]
        }
      },
      "uniqueConstraints": {},
      "checkConstraint": {}
    },
    "smsReminders": {
      "name": "smsReminders",
      "columns": {
        "id": {
          "name": "id",
          "type": "int",
          "primaryKey": false,
          "notNull": true,
          "autoincrement": true
        },
        "enrollmentId": {
          "name": "enrollmentId",
          "type": "int",
          "primaryKey": false,
          "notNull": true,
          "autoincrement": false
        },
        "userId": {
          "name": "userId",
          "type": "int",
          "primaryKey": false,
          "notNull": true,
          "autoincrement": false
        },
        "phoneNumber": {
          "name": "phoneNumber",
          "type": "varchar(20)",
          "primaryKey": false,
          "notNull": true,
          "autoincrement": false
        },
        "reminderType": {
          "name": "reminderType",
          "type": "enum('enrollment_confirmation','payment_reminder','training_reminder','post_training')",
          "primaryKey": false,
          "notNull": true,
          "autoincrement": false
        },
        "status": {
          "name": "status",
          "type": "enum('pending','sent','failed')",
          "primaryKey": false,
          "notNull": false,
          "autoincrement": false,
          "default": "'pending'"
        },
        "sentAt": {
          "name": "sentAt",
          "type": "timestamp",
          "primaryKey": false,
          "notNull": false,
          "autoincrement": false
        },
        "createdAt": {
          "name": "createdAt",
          "type": "timestamp",
          "primaryKey": false,
          "notNull": true,
          "autoincrement": false,
          "default": "(now())"
        }
      },
      "indexes": {},
      "foreignKeys": {},
      "compositePrimaryKeys": {
        "smsReminders_id": {
          "name": "smsReminders_id",
          "columns": [
            "id"
          ]
        }
      },
      "uniqueConstraints": {},
      "checkConstraint": {}
    },
    "users": {
      "name": "users",
      "columns": {
        "id": {
          "name": "id",
          "type": "int",
          "primaryKey": false,
          "notNull": true,
          "autoincrement": true
        },
        "openId": {
          "name": "openId",
          "type": "varchar(64)",
          "primaryKey": false,
          "notNull": true,
          "autoincrement": false
        },
        "name": {
          "name": "name",
          "type": "text",
          "primaryKey": false,
          "notNull": false,
          "autoincrement": false
        },
        "email": {
          "name": "email",
          "type": "varchar(320)",
          "primaryKey": false,
          "notNull": false,
          "autoincrement": false
        },
        "phone": {
          "name": "phone",
          "type": "varchar(20)",
          "primaryKey": false,
          "notNull": false,
          "autoincrement": false
        },
        "loginMethod": {
          "name": "loginMethod",
          "type": "varchar(64)",
          "primaryKey": false,
          "notNull": false,
          "autoincrement": false
        },
        "role": {
          "name": "role",
          "type": "enum('user','admin')",
          "primaryKey": false,
          "notNull": true,
          "autoincrement": false,
          "default": "'user'"
        },
        "providerType": {
          "name": "providerType",
          "type": "enum('nurse','doctor','pharmacist','paramedic','lab_tech','respiratory_therapist','midwife','other')",
          "primaryKey": false,
          "notNull": false,
          "autoincrement": false
        },
        "userType": {
          "name": "userType",
          "type": "enum('individual','institutional','parent')",
          "primaryKey": false,
          "notNull": false,
          "autoincrement": false,
          "default": "'individual'"
        },
        "createdAt": {
          "name": "createdAt",
          "type": "timestamp",
          "primaryKey": false,
          "notNull": true,
          "autoincrement": false,
          "default": "(now())"
        },
        "updatedAt": {
          "name": "updatedAt",
          "type": "timestamp",
          "primaryKey": false,
          "notNull": true,
          "autoincrement": false,
          "onUpdate": true,
          "default": "(now())"
        },
        "lastSignedIn": {
          "name": "lastSignedIn",
          "type": "timestamp",
          "primaryKey": false,
          "notNull": true,
          "autoincrement": false,
          "default": "(now())"
        }
      },
      "indexes": {},
      "foreignKeys": {},
      "compositePrimaryKeys": {
        "users_id": {
          "name": "users_id",
          "columns": [
            "id"
          ]
        }
      },
      "uniqueConstraints": {
        "users_openId_unique": {
          "name": "users_openId_unique",
          "columns": [
            "openId"
          ]
        }
      },
      "checkConstraint": {}
    }
  },
  "views": {},
  "_meta": {
    "schemas": {},
    "tables": {},
    "columns": {}
  },
  "internal": {
    "tables": {},
    "indexes": {}
  }
}